baredl/__init__.py
baredl/config.py
baredl/core.py
baredl/cuda.py
baredl/data.py
baredl/functions.py
baredl/layers.py
baredl/metrics.py
baredl/models.py
baredl/optimisers.py
baredl/transforms.py
baredl/utils.py
baredl-0.0.4.dist-info/METADATA
baredl-0.0.4.dist-info/RECORD
baredl-0.0.4.dist-info/WHEEL
baredl-0.0.4.dist-info/top_level.txt
